logic_asts/__init__.py
logic_asts/base.py
logic_asts/ltl.py
logic_asts/py.typed
logic_asts/spec.py
logic_asts/stl_go.py
logic_asts/strel.py
logic_asts/utils.py
logic_asts/grammars/__init__.py
logic_asts/grammars/base.lark
logic_asts/grammars/ltl.lark
logic_asts/grammars/stl_go.lark
logic_asts/grammars/strel.lark
logic_asts-1.4.1.dist-info/METADATA
logic_asts-1.4.1.dist-info/WHEEL
logic_asts-1.4.1.dist-info/licenses/LICENSE
logic_asts-1.4.1.dist-info/RECORD
