Metadata-Version: 2.4
Name: logic-asts
Version: 1.4.1
Summary: Grammars and parsers for various logic
Author-email: Anand Balakrishnan <anandbala1597@gmail.com>
License: BSD 2-Clause License
License-File: LICENSE
Requires-Python: >=3.10
Requires-Dist: attrs>=25.3.0
Requires-Dist: lark>=1.2.2
Requires-Dist: typing-extensions>=4.13.0
